{
  "articles": [
    {
      "id": "betaflight-turkce-rehber",
      "title": "FPV Drone Başlangıç Rehberi: Betaflight Türkçe Rehber",
      "category": "software",
      "content": "# FPV Drone Başlangıç Rehberi: Betaflight Türkçe Rehber\n\n## Giriş\n\nBetaflight, FPV drone pilotlarının en yaygın olarak kullandığı ücretsiz ve açık kaynak kodlu bir yazılımdır. Çoğu flight controller (FC) ile uyumlu çalışan bu yazılım, drone'un davranışını optimize etmek ve kişiselleştirilmiş ayarlar yapabilmek için kullanılır. Bu rehberde, yeni başlayanlar için Betaflight kullanımının temel adımlarına odaklanacağız.\n\n## 1. Betaflight Yazılımını Kurma\n\nBetaflight Configurator, Betaflight firmware'ini yüklemek ve drone ayarlarını yapmak için gereken bilgisayar yazılımıdır.\n\n### Betaflight Configurator Nasıl Kurulur?\n\n1. [Betaflight Configurator](https://github.com/betaflight/betaflight-configurator/releases) adresine gidin\n2. İşletim sisteminize uygun sürümü indirin (Windows, macOS veya Linux)\n3. Yazılımı bilgisayarınıza yükleyin ve kurulum tamamlandıktan sonra çalıştırın\n\n#### USB Sürücülerini Yükleme\n\nBazı flight controller'ların Betaflight ile bağlanabilmesi için ek USB sürücülerine ihtiyacınız olabilir.\n\n- [ImpulseRC Driver Fixer](https://impulserc.com/pages/downloads) aracını kullanarak gerekli USB sürücülerini yükleyebilirsiniz.\n\n## 2. Firmware Güncellemesi (Update Firmware)\n\nBetaflight firmware'i güncellemek, flight controller'ınızın en son özelliklere ve iyileştirmelere sahip olmasını sağlar.\n\n![Firmware Güncelleme](img/firmware.jpg)\n*Betaflight firmware güncelleme ekranı*\n\n### Firmware Güncelleme Adımları\n\n1. \"Firmware Flasher\" sekmesine tıklayın\n2. Flight controller modelinizi seçin (örneğin, \"MATEKF722\")\n3. En son sürümü seçmek için \"Load Firmware [Online]\" tuşuna tıklayın\n4. \"Flash Firmware\" butonuna basarak firmware'i yükleyin\n   - Yükleme sırasında drone'unuzun USB bağlantısının kesilmemesine dikkat edin\n\n## 3. Drone'u Betaflight'a Bağlama\n\n### Bağlantı Adımları\n\n1. Drone'unuzu USB kablosu ile bilgisayarınıza bağlayın\n2. Betaflight Configurator'ı çalıştırın\n3. \"Connect\" tuşuna tıklayarak drone'unuzu yazılıma bağlayın\n\nEğer bağlantıda sorun yaşıyorsanız:\n\n- USB kablonuzun veri transferi yapabildiğinden emin olun\n- Sürücüleri kontrol edin\n\n## 4. Betaflight Arayüzüne Genel Bakış\n\n### Betaflight Sekmeleri ve Fonksiyonları\n\n| **Sekme** | **Fonksiyon** |\n|-----------|---------------|\n| **Setup** | Temel ayarlar ve sistem durumu görülür |\n| **Ports** | UART portlarının yapılandırılması |\n| **Configuration** | Drone'un genel yapılandırması (ESC protokolü, motor dizilimi vb.) |\n| **Receiver** | Kumanda alıcısı ayarları ve kanal haritalama |\n| **Modes** | Uçuş modlarının atanması (Acro, Horizon, Arm vb.) |\n| **OSD** | Gözlük ekranında (On-Screen Display) gösterilecek bilgilerin ayarlanması |\n| **Motors** | Motor testi ve kalibrasyonu |\n| **CLI** | Komut satırından ileri seviye ayarlar yapılır |\n\n## 5. Temel Ayarları Yapılandırma\n\n### Ports (UART Ayarları)\n\nUçuş kontrolcüsü ile alıcı (receiver), VTX ya da GPS gibi cihazlar arasındaki iletişim UART portları ile sağlanır.\n\n![UART Portları](img/ports.jpg)\n*UART port yapılandırması*\n\n**Nasıl Yapılır?**\n1. \"Ports\" sekmesine gidin\n2. Kullanılan cihazların uygun UART portunu etkinleştirin\n\n### Configuration (Drone Yapılandırması)\n\n![Configuration Sekmesi](img/bhbh.jpg)\n*Configuration sekmesi ayarları*\n\n- **Motor Protokolü**: İdeal olarak DShot protokolü seçilir (DShot600 veya DShot300)\n- **ESC Kalibrasyonu**: Motorların ve ESC'lerin doğru çalışması için kalibre edilmesi gerekir\n- **FailSafe**: Bağlantı kopması durumunda drone'un ne yapacağını tanımlar\n\n### Receiver (Kumanda Ayarları)\n\n![Receiver Ayarları](img/rec.jpg)\n*Receiver sekmesi ayarları*\n\n- Receiver sekmesinde kumandanızın kanallarını Betaflight'a tanıtın\n- Kanal haritası: Genellikle \"AETR\" kullanılır (Aileron, Elevator, Throttle, Rudder)\n\n### Modes (Uçuş Modları)\n\n![Uçuş Modları](img/modes.jpg)\n*Uçuş modları atama ekranı*\n\n- **Arm**: Drone'un motorlarını çalıştırmak için atanır\n- **Acro**: Serbest ve manuel uçuş modu\n- **Horizon**: Stabilizasyon destekli uçuş modu\n- **Angle**: Yeni başlayanlar için tam stabilizasyon sağlar\n\n### OSD (Ekran Ayarları)\n\n![OSD Ayarları](img/osd.jpg)\n*OSD (On-Screen Display) ayarları*\n\nDrone'unuzun gözlüğünde görünecek bilgileri ayarlayabilirsiniz:\n- Batarya voltajı\n- Uçuş süresi\n- GPS bilgileri\n- RSSI sinyal gücü\n\n## 6. Motor Testi ve Kalibrasyon\n\n### Motor Testi\n\n![Motor Testi](img/motor.jpg)\n*Motor test ekranı*\n\n- \"Motors\" sekmesine gidin\n- Motorları manuel olarak kontrol edin ve doğru motorun doğru yönde döndüğünü onaylayın\n\n### ESC Kalibrasyonu\n\n1. ESC'lerinizi doğru protokolle (DShot, Multishot vb.) kullanın\n2. Kalibrasyon yaparak motorlardan maksimum verim alın\n\n## 7. Son Kontrol ve İlk Uçuş\n\n### Uçuş Öncesi Kontroller\n\n1. Tüm ayarları kontrol edin\n2. Drone'un vidalarını ve bağlantı noktalarını sıkın\n3. Kumanda ile \"Arm\" moduna geçin ve motorlarını test edin\n4. İlk uçuşu düz bir arazide ve düşük gazla yapın\n\n## Sonuç\n\nBetaflight, FPV drone'ların performansını optimize etmek için muazzam bir aracıdır. Bu temel bilgilerle başlayarak, zamanla daha karmaşık ayarlara ve optimizasyonlara geçebilirsiniz. Uygulamaları dikkatlice yaparak uçuş deneyiminizi güvenli ve keyifli hale getirebilirsiniz.\n\n## Önemli Notlar\n\n- Her değişiklikten sonra ayarları kaydetmeyi unutmayın\n- İlk uçuşlarda düşük gaz kullanın\n- Güvenlik her zaman öncelikli olmalıdır\n- Sorun yaşadığınızda topluluk forumlarından yardım alın\n\n## Kaynaklar ve İleri Okuma\n\n- [Betaflight Resmi Wiki](https://github.com/betaflight/betaflight/wiki)\n- [FPV Drone Türkçe Rehber](https://fpvdrone.tr/betaflight-turkce-rehber/)\n- Betaflight topluluk forumları\n- FPV uçuş güvenlik rehberleri\n\n---\n\n*Bu rehber, FPV drone başlangıç seviyesi pilotlar için hazırlanmıştır. İleri seviye ayarlar için Betaflight Wiki ve topluluk kaynaklarını inceleyiniz.*",
      "tags": [
        "betaflight",
        "fpv",
        "drone",
        "software",
        "konfigürasyon",
        "türkçe",
        "rehber",
        "başlangıç"
      ],
      "createdAt": "2025-01-08T00:00:00.000Z",
      "updatedAt": "2025-01-08T00:00:00.000Z",
      "images": [
        {
          "url": "img/firmware.jpg",
          "alt": "Firmware Güncelleme",
          "caption": "Betaflight firmware güncelleme ekranı"
        },
        {
          "url": "img/ports.jpg",
          "alt": "UART Portları",
          "caption": "UART port yapılandırması"
        },
        {
          "url": "img/bhbh.jpg",
          "alt": "Configuration Sekmesi",
          "caption": "Configuration sekmesi ayarları"
        },
        {
          "url": "img/rec.jpg",
          "alt": "Receiver Ayarları",
          "caption": "Receiver sekmesi ayarları"
        },
        {
          "url": "img/modes.jpg",
          "alt": "Uçuş Modları",
          "caption": "Uçuş modları atama ekranı"
        },
        {
          "url": "img/osd.jpg",
          "alt": "OSD Ayarları",
          "caption": "OSD (On-Screen Display) ayarları"
        },
        {
          "url": "img/motor.jpg",
          "alt": "Motor Testi",
          "caption": "Motor test ekranı"
        }
      ],
      "author": "FEZA Drone Sözlüğü",
      "source": "https://fpvdrone.tr/betaflight-turkce-rehber/",
      "wordCount": 1200,
      "readingTime": "6 dakika",
      "difficulty": "Başlangıç",
      "relatedArticles": [
        "betaflight-konfigürasyonu",
        "fpv-drone-baslangic",
        "esc-kalibrasyonu",
        "motor-testi"
      ]
    },
    {
      "id": "oscar-liang-betaflight-setup",
      "title": "FPV Drone'lar İçin Betaflight Firmware Kurulumu - Oscar Liang Rehberi",
      "category": "software",
      "content": "# FPV Drone'lar İçin Betaflight Firmware Kurulumu - Oscar Liang Rehberi\n\n## Giriş\n\nBu rehberde, FPV drone'unuzu inşa ettikten sonra ilk uçuş için Betaflight'ı nasıl kuracağınızı ve flight controller'ınızı nasıl yapılandıracağınızı göstereceğim. Betaflight, FPV drone'lar (genel olarak multirotor'lar) için özel olarak tasarlanmış mükemmel bir açık kaynak flight controller yazılımıdır.\n\n![Betaflight Kurulum Rehberi](img/betaflight-setup-tutorial-basic-beginner.jpg)\n*FPV drone'lar için Betaflight firmware kurulum rehberi*\n\n## Başlamadan Önce\n\nBu rehber Betaflight 4.4'e dayanmaktadır. Sadece aşağıdaki kriterleri karşılayan drone'unuz için geçerlidir:\n\n- Quadcopter (4 motor)\n- Flight controller'ınız Betaflight ile uyumlu\n- Serial radio receiver kullanıyorsunuz (Crossfire, ExpressLRS, Tracer, Ghost vb.)\n- ESC'niz BLHeli_S veya BLHeli_32\n\n**Güvenlik Uyarısı:** Başlamadan önce tüm propeller'ları çıkarın ve VTX'e anten taktığınızdan emin olun (anten olmadan VTX'i güçlendirirseniz aşırı ısınabilir ve zarar görebilir).\n\n## Betaflight Configurator Kurulumu\n\nBetaflight Configurator, flight controller'ı flash etmek ve Betaflight'ı kurmak için kullanmamız gereken yazılımdır.\n\n**En son sürümü indirin:** [https://github.com/betaflight/betaflight-configurator/releases/latest](https://github.com/betaflight/betaflight-configurator/releases/latest)\n\n### Desteklenen İşletim Sistemleri\n\n| İşletim Sistemi | Dosya Adı |\n|-----------------|-----------|\n| Windows (8, 10, 11) | betaflight-configurator-[version]_win64-installer.exe |\n| Mac OS X | betaflight-configurator_[version]_macOS.dmg |\n| Ubuntu, Debian | betaflight-configurator_[version]_amd64.deb |\n| Red Hat, Fedora, CentOS | betaflight-configurator-[version].x86_64.rpm |\n| Diğer Linux | betaflight-configurator_[version]_linux64-portable.zip |\n| Android | betaflight-configurator-debug-[version]_android.apk |\n\nSol paneldeki Options'a gidin ve şu seçenekleri etkinleştirin:\n\n![Betaflight Configurator Seçenekleri](img/betaflight-configurator-10.8.0-options.jpg)\n*Betaflight Configurator ayarları*\n\n## Firmware Güncelleme\n\nÖnerilerimi takip ederek flight controller (FC) satın aldıysanız, zaten Betaflight önceden yüklü olarak gelmelidir. Ancak eski bir sürüm olabilir, bu yüzden hata düzeltmeleri ve yeni özellikler için en son Betaflight sürümünde kalmak her zaman iyi bir fikirdir.\n\n**Önemli:** Flight controller'a firmware flash etmeden önce, mevcut yapılandırmanın yedeğini aldığınızdan emin olun. Bu, bir şeyler ters giderse orijinal durumuna geri dönmenizi sağlar.\n\n![Firmware Flasher](img/betaflight-4.4-configurator-10.9.0-firmware-flasher-auto-detect-online.jpg)\n*Betaflight firmware flasher ekranı*\n\n## İlk Kez Betaflight Yapılandırması\n\nİşleri basit tutmak için, sadece temel ayarları yapılandıracağız - sizi havaya çıkarmak için yeterli. Daha sonra isterseniz diğer ayarları keşfedebilirsiniz.\n\n**Önemli!** Quad'ınızı tezgah üzerinde yapılandırırken kazayı önlemek için tüm propeller'ların çıkarıldığından emin olun.\n\n### Flight Controller'ı Bilgisayara Bağlama\n\nUSB kablosunu FC'ye bağlayarak, aynı zamanda güç de sağlanır, LiPo bataryayı takmanıza gerek yoktur.\n\n![USB Bağlantısı](img/STP-Hobby-Armor-5-FPV-Drone-rushfpv-fc-usb.jpg)\n*Flight controller'ı USB ile bilgisayara bağlama*\n\nFC bilgisayara bağlandığında, Configurator'da yeni bir COM Port görünmelidir. Bu yeni COM Port'u seçin ve \"Connect\"e tıklayın. Örnekte COM11 var, ancak sizin durumunuzda muhtemelen farklı olacaktır.\n\n![COM Port Bağlantısı](img/betaflight-Setup-configurator-connect-com-port.jpg)\n*Betaflight Configurator'da COM port seçimi*\n\n**Pro İpucu:** Veri USB kablosu kullandığınızdan emin olun. İki tür USB kablosu vardır: sadece şarj kabloları ve veri kabloları. Betaflight Configurator ile iletişim kurmak için veri kablosu kullanmanız gerekir.\n\n### Setup (Kurulum)\n\nBetaflight'a başarıyla bağlandığınızda, quadcopter'in 3D modeli ile Setup sekmesi karşılayacaktır. Burada flight controller durumunun temel bir genel bakışını alırsınız ve birkaç temel fonksiyona erişiminiz olur.\n\nBurada yapmanız gereken birkaç şey var:\n\n1. Quadcopter/FC'nizi düz bir yüzeye koyun, sonra \"Calibrate Accelerometer\"a basın - bu sadece firmware flash ettiğinizde bir kez yapılması gerekir\n2. Şimdi quad'ı ellerinizle hareket ettirin (ileri geri pitch, sağa sola roll, yaw vb. deneyin), 3D model hareketleri takip etmelidir\n\n![Setup Ekranı](img/betaflight-configurator-setup-10.8.jpg)\n*Betaflight Setup sekmesi - Accelerometer kalibrasyonu*\n\n3D model quad'ınızla aynı şekilde hareket etmiyorsa, birkaç şey anlamına gelebilir, belki FC'niz ters çevrilmiş veya yanlış yöne monte edilmiş (örneğin FC'deki ok ileriye bakmıyor). Doğru olana kadar board'u döndürmeyi deneyin.\n\n### Presets (Ön Ayarlar)\n\nHerhangi bir değişiklik yapmadan önce, mevcut ayarlarınızın yedeğini almak her zaman iyi bir fikirdir. Bunu Presets sekmesinde yapabilirsiniz.\n\n![Presets Sekmesi](img/betaflight-4.3-presets-save-backup-load-cli-diff.jpg)\n*Betaflight Presets - Ayarları yedekleme ve yükleme*\n\nPresets ayrıca Betaflight'ta son derece yararlı bir özelliktir.\n\n### Voltaj Kalibrasyonu\n\nBir batarya alın, voltajını batarya kontrol cihazı veya multimetre ile kontrol edin.\n\nSonra drone'a takın (önce propeller'ları çıkarın!). Configurator'da bildirilen voltaj ölçtüğünüz voltajla aynı değilse, Betaflight'taki voltaj sensörünü kalibre etmelisiniz.\n\n![Voltaj Kalibrasyonu](img/firmware.jpg)\n*Betaflight voltaj kalibrasyonu ekranı*\n\nBunu yapmak için sol paneldeki \"Power & Battery\" sekmesine gidin. Sağ alttaki Calibration butonuna tıklayın. Açılan kutuda ölçülen voltajı girin, sonra Calibrate'e tıklayın ve yeni bir voltaj ölçeği uygulamasını isteyecektir. Bu kadar.\n\n## Temel Ayarlar\n\n### Ports (Portlar)\n\nPorts sekmesinde, UART (TX ve RX pad'leri) veya soft serial aracılığıyla flight controller'a bağlı tüm çevre birimlerini (harici cihazlar) yapılandırabilirsiniz. Burada receiver ve VTX bağlantılarımızı yapılandırmak istiyoruz.\n\n![UART Portları](img/ports.jpg)\n*Betaflight UART port yapılandırması*\n\nYapmanız gereken sadece 2 şey var:\n\n1. **Analog VTX** kullanıyorsanız ve VTX kontrolü için SmartAudio veya IRC Tramp kablosunu bağladıysanız, VTX'i bağladığınız UART için Peripherals altında \"**VTX (TBS SmartAudio)**\" veya \"**VTX (IRC Tramp)**\" seçmelisiniz.\n2. **Serial receiver** kullanıyorsanız (Crossfire, ExpressLRS, Tracer, Ghost vb.), receiver'ı bağladığınız UART için \"**Serial RX**\" seçmelisiniz.\n\n### Configuration (Yapılandırma)\n\nConfiguration sekmesinde drone'unuzun genel yapılandırmasını ayarlarsınız:\n\n![Configuration Sekmesi](img/bhbh.jpg)\n*Betaflight Configuration sekmesi ayarları*\n\n- **Motor Protokolü**: DShot600 veya DShot300 gibi DShot protokolü seçin\n- **ESC Kalibrasyonu**: Motorların ve ESC'lerin doğru çalışması için kalibre edin\n- **FailSafe**: Bağlantı kopması durumunda drone'un ne yapacağını tanımlayın\n\n### Receiver (Alıcı)\n\nReceiver sekmesinde kumandanızın kanallarını Betaflight'a tanıtın:\n\n![Receiver Ayarları](img/rec.jpg)\n*Betaflight Receiver sekmesi ayarları*\n\n- Kanal haritası: Genellikle \"AETR\" kullanılır (Aileron, Elevator, Throttle, Rudder)\n- Receiver tipini doğru seçin (SBUS, CRSF, vb.)\n\n### Modes (Modlar)\n\nModes sekmesinde uçuş modlarını atayın:\n\n![Uçuş Modları](img/modes.jpg)\n*Betaflight Modes sekmesi - Uçuş modları atama*\n\n- **Arm**: Drone'un motorlarını çalıştırmak için atanır\n- **Acro**: Serbest ve manuel uçuş modu\n- **Horizon**: Stabilizasyon destekli uçuş modu\n- **Angle**: Yeni başlayanlar için tam stabilizasyon sağlar\n\n### Motors (Motorlar)\n\nMotors sekmesinde motor testi yapın:\n\n![Motor Testi](img/motor.jpg)\n*Betaflight Motors sekmesi - Motor test ekranı*\n\n- Motorları manuel olarak kontrol edin\n- Doğru motorun doğru yönde döndüğünü onaylayın\n- Motor sırasını kontrol edin\n\n### OSD (Ekran Üzeri Gösterge)\n\nOSD sekmesinde drone'unuzun gözlüğünde görünecek bilgileri ayarlayın:\n\n![OSD Ayarları](img/osd.jpg)\n*Betaflight OSD sekmesi - Ekran üzeri gösterge ayarları*\n\n- Batarya voltajı\n- Uçuş süresi\n- GPS bilgileri\n- RSSI sinyal gücü\n\n## Güvenlik Kontrolleri\n\nİlk uçuştan önce:\n\n1. Tüm ayarları kontrol edin\n2. Drone'un vidalarını ve bağlantı noktalarını sıkın\n3. Kumanda ile \"Arm\" moduna geçin ve motorları test edin\n4. İlk uçuşu düz bir arazide ve düşük gazla yapın\n\n## Sonuç\n\nBu rehber, FPV drone'unuzu ilk uçuş için hazırlamanız için gerekli temel Betaflight ayarlarını kapsar. Bu temel bilgilerle başlayarak, zamanla daha karmaşık ayarlara ve optimizasyonlara geçebilirsiniz.\n\n**Önemli Notlar:**\n- Her değişiklikten sonra ayarları kaydetmeyi unutmayın\n- İlk uçuşlarda düşük gaz kullanın\n- Güvenlik her zaman öncelikli olmalıdır\n- Sorun yaşadığınızda topluluk forumlarından yardım alın\n\n## Kaynaklar\n\n- [Oscar Liang - Betaflight Firmware Setup](https://oscarliang.com/betaflight-firmware-setup/)\n- [Betaflight Resmi Wiki](https://github.com/betaflight/betaflight/wiki)\n- Betaflight topluluk forumları\n\n---\n\n*Bu rehber, Oscar Liang'ın orijinal İngilizce rehberinden Türkçe'ye çevrilmiş ve FPV drone başlangıç seviyesi pilotlar için hazırlanmıştır.*",
      "tags": [
        "oscar-liang",
        "betaflight",
        "fpv",
        "drone",
        "software",
        "kurulum",
        "türkçe",
        "rehber",
        "başlangıç"
      ],
      "createdAt": "2025-01-08T00:00:00.000Z",
      "updatedAt": "2025-01-08T00:00:00.000Z",
      "images": [
        {
          "url": "img/betaflight-setup-tutorial-basic-beginner.jpg",
          "alt": "Betaflight Kurulum Rehberi",
          "caption": "FPV drone'lar için Betaflight firmware kurulum rehberi"
        },
        {
          "url": "img/betaflight-configurator-10.8.0-options.jpg",
          "alt": "Betaflight Configurator Seçenekleri",
          "caption": "Betaflight Configurator ayarları"
        },
        {
          "url": "img/betaflight-4.4-configurator-10.9.0-firmware-flasher-auto-detect-online.jpg",
          "alt": "Firmware Flasher",
          "caption": "Betaflight firmware flasher ekranı"
        },
        {
          "url": "img/STP-Hobby-Armor-5-FPV-Drone-rushfpv-fc-usb.jpg",
          "alt": "USB Bağlantısı",
          "caption": "Flight controller'ı USB ile bilgisayara bağlama"
        },
        {
          "url": "img/betaflight-Setup-configurator-connect-com-port.jpg",
          "alt": "COM Port Bağlantısı",
          "caption": "Betaflight Configurator'da COM port seçimi"
        },
        {
          "url": "img/betaflight-configurator-setup-10.8.jpg",
          "alt": "Setup Ekranı",
          "caption": "Betaflight Setup sekmesi - Accelerometer kalibrasyonu"
        },
        {
          "url": "img/betaflight-4.3-presets-save-backup-load-cli-diff.jpg",
          "alt": "Presets Sekmesi",
          "caption": "Betaflight Presets - Ayarları yedekleme ve yükleme"
        },
        {
          "url": "img/firmware.jpg",
          "alt": "Voltaj Kalibrasyonu",
          "caption": "Betaflight voltaj kalibrasyonu ekranı"
        },
        {
          "url": "img/ports.jpg",
          "alt": "UART Portları",
          "caption": "Betaflight UART port yapılandırması"
        },
        {
          "url": "img/bhbh.jpg",
          "alt": "Configuration Sekmesi",
          "caption": "Betaflight Configuration sekmesi ayarları"
        },
        {
          "url": "img/rec.jpg",
          "alt": "Receiver Ayarları",
          "caption": "Betaflight Receiver sekmesi ayarları"
        },
        {
          "url": "img/modes.jpg",
          "alt": "Uçuş Modları",
          "caption": "Betaflight Modes sekmesi - Uçuş modları atama"
        },
        {
          "url": "img/motor.jpg",
          "alt": "Motor Testi",
          "caption": "Betaflight Motors sekmesi - Motor test ekranı"
        },
        {
          "url": "img/osd.jpg",
          "alt": "OSD Ayarları",
          "caption": "Betaflight OSD sekmesi - Ekran üzeri gösterge ayarları"
        }
      ],
      "author": "FEZA Drone Sözlüğü (Oscar Liang'dan çeviri)",
      "source": "https://oscarliang.com/betaflight-firmware-setup/",
      "wordCount": 2500,
      "readingTime": "12 dakika",
      "difficulty": "Başlangıç",
      "relatedArticles": [
        "betaflight-turkce-rehber",
        "betaflight-konfigürasyonu",
        "fpv-drone-baslangic"
      ]
    },
    {
      "id": "fiber-optik-drone-teknolojisi",
      "title": "8 Maddede Fiber Optik Drone Teknolojisi",
      "category": "teknoloji",
      "content": "# 8 Maddede Fiber Optik Drone Teknolojisi\n\n## 1. Giriş\n\nDrone teknolojisi, son on yıl içerisinde muazzam bir gelişme göstererek havacılık dünyasında köklü değişiklikler yarattı. İlk zamanlarda hobi amaçlı veya sadece görüntü kaydetmek için kullanılan dronelar, zamanla çok çeşitli sektörlerin ihtiyacına yanıt verebilen güçlü birer iş aracı hâline geldi. Örneğin inşaat, tarım, lojistik, güvenlik ve savunma gibi sektörlerde drone kullanımı bir hayli yaygınlaşmış durumda.\n\n![Fiber Optik Drone Genel Bakış](img/fiber-optik-drone-overview.jpg)\n*Fiber optik drone teknolojisi - Geleceğin iletişim çözümü*\n\nTeknolojik gelişmeler ve kullanıcı talepleri doğrultusunda, droneların donanım ve yazılım özelliklerinde de büyük ilerlemeler kaydedildi. Yüksek çözünürlüklü kameralar, uzun menzilli uçuş ve kablosuz veri aktarım teknolojileri bu alanda yaşanan dönüşüme öncülük etti. Ancak bu noktada yeni bir konsept olan \"fiber optik drone\" kavramı, sunduğu farklı iletişim modeliyle dikkat çekiyor.\n\n## 2. Fiber Optik Drone Nedir?\n\nFiber optik drone, basit bir tanımla; drone ile kontrol istasyonu arasındaki veri (veya bazı sistemlerde güç) iletişiminin fiber optik kablo üzerinden yapıldığı, kablosuz iletişimden farklı bir tasarıma sahip drone türüdür. Genellikle kablosuz iletişimde radyo frekans (RF) dalgalarından yararlanılır. Oysa fiber optik drone sisteminde, bilgi ışık sinyalleri şeklinde taşınır.\n\n![Fiber Optik İletişim Sistemi](img/fiber-optik-communication.jpg)\n*Fiber optik drone iletişim sistemi - Işık sinyalleri ile veri aktarımı*\n\nFiber optik kablolar, klasik bakır kabloların aksine veriyi daha yüksek bant genişliği ve daha düşük kayıpla iletebilir. Ayrıca elektromanyetik girişimlere (EMI) karşı daha korunaklıdır. Bu, dronenun bulunduğu çevrede yüksek frekanslı cihazların veya sinyal engelleyici unsurların varlığında dahi kararlı bir iletişim sağlar.\n\n![Fiber Optik Kablo Sistemi](img/fiber-optik-cable-system.jpg)\n*Fiber optik kablo sistemi - Yüksek bant genişliği ve güvenli iletişim*\n\nBazı fiber optik drone tasarımlarında yalnızca veri aktarımı yapılırken, bazılarında kablo üzerinden drone'un bataryasına ek güç sağlanır. Böylece drone, çok daha uzun süre havada kalabilir. Bu özellik, özellikle sabit gözetleme veya kesintisiz gözlem gerektiren operasyonlar için oldukça caziptir.\n\n## 3. Neden Trend Oldu?\n\n### 3.1. Veri Güvenliği ve Gizlilik\n\nKablosuz veri iletişimi, radyo dalgaları aracılığıyla gerçekleştirilir ve üçüncü tarafların bu sinyalleri engelleyebilmesi, karıştırabilmesi veya dinleyebilmesi teknik olarak mümkündür. Fiber optik kablo üzerinden sağlanan veri aktarımı ise fiziksel bir hattı esas alır. Bu hat üzerinde dışarıdan müdahale ya da veri sızıntısı yapmak çok daha zordur.\n\n![Fiber Optik Kontrol İstasyonu](img/fiber-optik-control-station.jpg)\n*Fiber optik drone kontrol istasyonu - Güvenli veri aktarımı*\n\nSavunma sanayii, güvenlik güçleri ve yüksek hassasiyette veri toplayan kurumlar için bu özellik kritik öneme sahiptir.\n\n### 3.2. Elektromanyetik Parazitlere Dayanıklılık\n\nEndüstriyel veya kentsel ortamlarda, elektromanyetik parazit kaynakları sıkça bulunur. Bu, kablosuz sinyallerde bozulmalara ve iletişim kesintilerine neden olabilir. Fiber optik sistemler, bu tür girişimlere karşı çok daha dayanıklıdır.\n\n![Fiber Optik Veri Aktarımı](img/fiber-optik-data-transmission.jpg)\n*Fiber optik sistemlerin elektromanyetik girişimlere dayanıklılığı*\n\n### 3.3. Yüksek Bant Genişliği\n\nFiber optik kablolar, kablosuz sistemlere kıyasla çok daha yüksek bant genişliği sunar. Bu, yüksek çözünürlüklü video, büyük veri dosyaları ve gerçek zamanlı veri aktarımı için kritik öneme sahiptir.\n\n## 4. Fiber Optik Drone'un Avantajları\n\n### 4.1. Kesintisiz İletişim\n\nFiber optik sistemler, elektromanyetik girişimlere karşı dayanıklı olduğu için kesintisiz iletişim sağlar. Bu özellik, kritik operasyonlarda hayati önem taşır.\n\n![Fiber Optik Drone Bileşenleri](img/fiber-optik-drone-components.jpg)\n*Fiber optik drone bileşenleri - Kesintisiz iletişim altyapısı*\n\n### 4.2. Güvenli Veri Aktarımı\n\nFiziksel kablo üzerinden yapılan veri aktarımı, dış müdahalelere karşı çok daha güvenlidir. Bu, askeri ve güvenlik uygulamalarında kritik öneme sahiptir.\n\n### 4.3. Uzun Menzil\n\nFiber optik kablolar, sinyal kaybı olmadan çok uzun mesafelere veri aktarabilir. Bu, drone'un çok daha uzak mesafelerde operasyon yapabilmesini sağlar.\n\n### 4.4. Yüksek Bant Genişliği\n\nFiber optik sistemler, kablosuz sistemlere kıyasla çok daha yüksek bant genişliği sunar. Bu, yüksek çözünürlüklü video ve büyük veri dosyalarının aktarımı için idealdir.\n\n## 5. Fiber Optik Drone'un Kullanım Alanları\n\n### 5.1. Savunma ve Güvenlik\n\nFiber optik drone'lar, askeri operasyonlarda ve güvenlik uygulamalarında yaygın olarak kullanılır. Güvenli veri aktarımı ve kesintisiz iletişim özellikleri, bu alanlarda kritik öneme sahiptir.\n\n![Fiber Optik Askeri Uygulama](img/fiber-optik-military-application.jpg)\n*Fiber optik drone askeri uygulamaları - Güvenli ve kesintisiz operasyonlar*\n\n### 5.2. Endüstriyel Denetim\n\nBüyük endüstriyel tesislerde, fiber optik drone'lar altyapı denetimi, güvenlik gözetimi ve acil müdahale operasyonlarında kullanılır.\n\n![Fiber Optik Endüstriyel Kullanım](img/fiber-optik-industrial-use.jpg)\n*Fiber optik drone endüstriyel uygulamaları - Altyapı denetimi ve güvenlik*\n\n### 5.3. Altyapı Gözetimi\n\nKöprüler, barajlar, enerji hatları gibi kritik altyapıların sürekli gözetimi için fiber optik drone'lar ideal çözümdür.\n\n![Fiber Optik Veri Aktarımı](img/fiber-optik-data-transmission.jpg)\n*Fiber optik drone altyapı gözetimi - Kritik tesislerin sürekli denetimi*\n\n### 5.4. Acil Müdahale\n\nDoğal afetler ve acil durumlarda, fiber optik drone'lar güvenli iletişim sağlayarak kurtarma operasyonlarını destekler.\n\n## 6. Dezavantajları\n\n### 6.1. Kablo Sınırı\n\nFiber optik drone'lar, fiziksel kablo ile sınırlıdır. Bu, drone'un hareket alanını kısıtlar ve manevra kabiliyetini azaltır.\n\n![Fiber Optik Kablo Sistemi](img/fiber-optik-cable-system.jpg)\n*Fiber optik kablo sınırlamaları - Hareket alanı kısıtlamaları*\n\n### 6.2. Lojistik Zorluklar\n\nKablo sarma ve bırakma mekanizmaları, sistemin karmaşıklığını artırır. Ayrıca kablo yönetimi için özel ekipman ve personel gerekir.\n\n### 6.3. Kablo Hassasiyeti\n\nFiber optik kablolar, fiziksel hasarlara karşı hassastır. Kablonun kopması veya zarar görmesi durumunda sistem çalışmaz hale gelir.\n\n### 6.4. Maliyet\n\nFiber optik kablo, optik dönüştürücüler, özel sarma mekanizmaları ve güç aktarım sistemleri gibi ek bileşenler, klasik kablosuz dronelara kıyasla daha yüksek bir bütçe gerektirir.\n\n### 6.5. Yedek Parça ve Onarım\n\nKablonun kopması veya optik dönüştürücülerin arızalanması gibi durumlarda sistem tamamen çalışmaz hâle gelebilir. Bu sebeple, sahada yedek kablo ve yedek parçaların bulundurulması, ek bakım ekibinin hazır olması gerekebilir.\n\n## 7. Gelecekte Fiber Optik Drone Teknolojisi\n\nFiber optik drone teknolojisi, gelecekte daha da gelişmeye ve yaygınlaşmaya aday görünüyor. Bunun arkasında birkaç neden sıralanabilir:\n\n### 7.1. Güvenlik İhtiyaçlarının Artışı\n\nDünya çapında artan güvenlik endişeleri ve asimetrik tehditler, kesintisiz ve yüksek güvenlikli veri aktarımı talebini destekliyor.\n\n![Fiber Optik İletişim Sistemi](img/fiber-optik-communication.jpg)\n*Gelecekte fiber optik drone teknolojisi - Artan güvenlik ihtiyaçları*\n\n### 7.2. Daha Dayanıklı Kablo ve Sarma Sistemleri\n\nAR-GE çalışmaları sayesinde fiber optik kabloların dayanıklılığı artacak, darbelere, aşınmaya ve bükülmeye karşı daha korunaklı hâle gelecek.\n\n### 7.3. Hibrit Güç Aktarımı\n\nKablolu güç aktarımının yanı sıra güneş panelleri, yakıt hücreleri veya diğer enerji kaynaklarıyla hibrit tasarımlar mümkün hale gelebilir.\n\n### 7.4. Artan Endüstriyel Talep\n\nÖnümüzdeki yıllarda drone teknolojisine talep artmaya devam edecek gibi görünüyor. Özellikle akıllı şehirler, büyük ölçekli endüstriyel tesisler ve ileri otomasyon uygulamalarında fiber optik drone'lar daha yaygın biçimde kullanılabilir.\n\n### 7.5. Yeni Nesil Sensör ve Kamera Sistemleri\n\n8K ve üstü çözünürlüklerde kamera sistemleri, çoklu spektral sensörler, LIDAR ve radar tabanlı görüntüleme üniteleri gibi donanımları drone'larda görmek gittikçe yaygınlaşıyor.\n\n## 8. Sonuç\n\nFiber optik drone, klasik kablosuz dronelardan ayrılan yenilikçi bir yaklaşım sunarak veri güvenliği, kesintisiz iletişim ve gerekirse kesintisiz güç aktarımı konularında önemli avantajlar barındırır. Özellikle savunma, güvenlik, endüstriyel denetimler ve altyapı gözetimi gibi kritik öneme sahip uygulamalarda öne çıkmaktadır.\n\n![Fiber Optik Drone Genel Bakış](img/fiber-optik-drone-overview.jpg)\n*Fiber optik drone teknolojisi - Geleceğin iletişim çözümü*\n\nAncak kablo sınırı, lojistik zorluklar, yüksek maliyet ve kablonun hassasiyeti gibi dezavantajlar da bu teknolojinin yaygın kullanımını kısmen sınırlamaktadır.\n\nBuna rağmen, fiber optik drone teknolojisinin geleceği oldukça parlak görünmektedir. Güvenlik ve kesintisiz veri aktarımının öne çıktığı birçok senaryoda, kablosuz dronelara göre daha üstün bir performans sergileyen fiber optik drone'lar, doğru planlama ve AR-GE çalışmalarıyla çok daha gelişmiş versiyonlara evrilebilir.\n\n**HUBSAN TEKNOLOJİ AŞ**, Türkiye'de diğer drone modellerinde olduğu gibi tek üretim yapma kabiliyetine sahip firmadır. Gerek sivil drone modellerinin üretimi gerekse askeri drone üretimleri konusunda ülkemizin en büyük sivil havacılık firması olan HUBSAN fiber optik drone üretimini de yapmaktadır.\n\nKendi projelerinizde yüksek bant genişliğine ve güvenliğe ihtiyaç duyuyorsanız, fiber optik drone teknolojisini mutlaka değerlendirmeli, bu alanda yapılan AR-GE ve üretici firmaların çözümlerini yakından takip etmelisiniz. Önümüzdeki dönemde, drone dünyasını dönüştürebilecek büyük yeniliklerden birinin de bu teknoloji olması son derece muhtemeldir.\n\n## Kaynaklar\n\n- [Drone.net.tr - 8 Maddede Fiber Optik Drone Teknolojisi](https://drone.net.tr/8-maddede-fiber-optik-drone-teknolojisi.html)\n- HUBSAN TEKNOLOJİ AŞ - Fiber Optik Drone Üretimi\n- Endüstriyel Drone Teknolojileri\n- Savunma Sanayii Drone Uygulamaları\n\n---\n\n*Bu rehber, fiber optik drone teknolojisinin temel özelliklerini, avantajlarını, dezavantajlarını ve gelecekteki potansiyelini kapsamlı bir şekilde ele almaktadır.*",
      "tags": [
        "fiber-optik",
        "drone",
        "teknoloji",
        "iletişim",
        "güvenlik",
        "endüstriyel",
        "askeri",
        "türkçe",
        "rehber"
      ],
      "createdAt": "2025-01-08T00:00:00.000Z",
      "updatedAt": "2025-01-08T00:00:00.000Z",
      "images": [
        {
          "url": "img/fiber-optik-drone-overview.jpg",
          "alt": "Fiber Optik Drone Genel Bakış",
          "caption": "Fiber optik drone teknolojisi - Geleceğin iletişim çözümü"
        },
        {
          "url": "img/fiber-optik-communication.jpg",
          "alt": "Fiber Optik İletişim Sistemi",
          "caption": "Fiber optik drone iletişim sistemi - Işık sinyalleri ile veri aktarımı"
        },
        {
          "url": "img/fiber-optik-cable-system.jpg",
          "alt": "Fiber Optik Kablo Sistemi",
          "caption": "Fiber optik kablo sistemi - Yüksek bant genişliği ve güvenli iletişim"
        },
        {
          "url": "img/fiber-optik-control-station.jpg",
          "alt": "Fiber Optik Kontrol İstasyonu",
          "caption": "Fiber optik drone kontrol istasyonu - Güvenli veri aktarımı"
        },
        {
          "url": "img/fiber-optik-data-transmission.jpg",
          "alt": "Fiber Optik Veri Aktarımı",
          "caption": "Fiber optik veri aktarımı - Kesintisiz ve yüksek hızlı iletişim"
        },
        {
          "url": "img/fiber-optik-drone-components.jpg",
          "alt": "Fiber Optik Drone Bileşenleri",
          "caption": "Fiber optik drone bileşenleri - Geleceğin teknoloji altyapısı"
        },
        {
          "url": "img/fiber-optik-military-application.jpg",
          "alt": "Fiber Optik Askeri Uygulama",
          "caption": "Fiber optik drone askeri uygulamaları - Güvenli ve kesintisiz operasyonlar"
        },
        {
          "url": "img/fiber-optik-industrial-use.jpg",
          "alt": "Fiber Optik Endüstriyel Kullanım",
          "caption": "Fiber optik drone endüstriyel uygulamaları - Altyapı denetimi ve güvenlik"
        }
      ],
      "author": "FEZA Drone Sözlüğü",
      "source": "https://drone.net.tr/8-maddede-fiber-optik-drone-teknolojisi.html",
      "wordCount": 3000,
      "readingTime": "15 dakika",
      "difficulty": "Orta",
      "relatedArticles": [
        "military-fpv-drone",
        "endüstriyel-drone",
        "drone-güvenlik-sistemleri"
      ]
    },
    {
      "id": "invisible-fiber-optic-cable-uav",
      "title": "İHA İçin Görünmez Fiber Optik Kablo Nedir?",
      "category": "teknoloji",
      "content": "# İHA İçin Görünmez Fiber Optik Kablo Nedir?\n\n## Giriş\n\nİHA (İnsansız Hava Aracı) teknolojisinin gelişmesiyle birlikte, drone'ların iletişim ve veri aktarım ihtiyaçları da artmıştır. Geleneksel kablosuz iletişim yöntemlerinin sınırlamaları, özellikle güvenlik ve güvenilirlik gerektiren uygulamalarda alternatif çözümler arayışını doğurmuştur. Bu noktada, görünmez fiber optik kablo teknolojisi devreye girmektedir.\n\n![Görünmez Fiber Optik Kablo](img/invisible-optical-cable.jpg)\n*İHA için görünmez fiber optik kablo - Şeffaf ve hafif tasarım*\n\n## Görünmez Fiber Optik Kablo Nedir?\n\nİHA için görünmez optik kablo, doğal optik fiberden çekilmiş, şeffaf naylon PA12 sıkı bir şekilde sarılmış fiber optik kablodur. Geleneksel optik fiberin avantajlarını özel malzemeler ve yapısal tasarımla birleştirerek görsel olarak olabildiğince göze çarpmamasını sağlar ve aynı zamanda veri iletimi ve iletişim bağlantıları için uygun olan hafif, yüksek esnekliğe ve parazit önleme özelliğine sahiptir.\n\n![Fabrika Şeffaf Fiber Optik Kablo](img/factory-transparent-fiber-optic-cable.jpg)\n*Fabrika üretimi şeffaf fiber optik kablo - Özel malzeme ve tasarım*\n\n## Görünmez Fiber Optik Kablonun Temel Özellikleri\n\n### 1. Görsel Gizlilik\nDrone'un içinde veya dışında kablolama yaparken fiber optik kablonun tespit edilmesini kolaylaştırmak için şeffaf veya yarı saydam malzemeler kullanılır. Bu özellik, özellikle askeri ve güvenlik uygulamalarında kritik öneme sahiptir.\n\n### 2. Hafiflik ve Kompakt Tasarım\nÇap genellikle küçüktür ve ağırlık hafiftir, bu da drone'nun genel yükünü azaltır ve uçuş performansını artırır. Bu özellik, özellikle uzun süreli uçuş operasyonlarında önemlidir.\n\n### 3. Yüksek Esneklik\nG657A2 fiberinin kullanımı nispeten mükemmel bükülme performansına sahiptir. Bu, drone'un karmaşık manevralar yapması gereken durumlarda kablonun zarar görmemesini sağlar.\n\n![İHA Görünmez Fiber Uygulaması](img/invisible-fiber-drone-application.jpg)\n*İHA'da görünmez fiber optik kablo uygulaması - Esnek ve dayanıklı tasarım*\n\n### 4. Düşük Sinyal Kaybı\nDüşük sinyal kaybı, uzun mesafeli iletimde düşük zayıflama ve yüksek bant genişliği sağlar, yüksek hızlı veri iletimini destekler. Bu özellik, gerçek zamanlı video akışı ve büyük veri dosyalarının aktarımı için idealdir.\n\n### 5. Hava Koşullarına Dayanıklılık\nAnti-ultraviyole, nem geçirmez, yanmaz ve diğer özelliklere sahip güçlü hava koşullarına dayanıklılık, çeşitli karmaşık ortamlarda uzun süre stabil olabilir.\n\n### 6. Elektromanyetik Koruması\nHarici elektromanyetik parazitin sinyal iletimi üzerindeki etkisini önlemek için iyi elektromanyetik koruma performansına sahip güçlü anti-parazit yeteneği.\n\n## Görünmez Fiber Optik Kablonun Uygulamaları\n\n### 1. Yüksek Hızlı Veri İletimi\nİHA ile yer istasyonu arasında video akışları, sensör verileri vb. dahil olmak üzere yüksek hızlı veri iletimi için kullanılır. Bu uygulama, özellikle gerçek zamanlı gözetleme ve keşif operasyonlarında kritik öneme sahiptir.\n\n![Görünmez Fiber Veri Aktarımı](img/invisible-fiber-data-transmission.jpg)\n*Görünmez fiber optik kablo ile yüksek hızlı veri aktarımı*\n\n### 2. İç Bileşen Bağlantıları\nKararlı ve güvenilir sinyal iletimini sağlamak için drone içindeki çeşitli bileşenler arasındaki bağlantı için kullanılır. Bu, drone'un elektronik sistemlerinin güvenilir çalışmasını sağlar.\n\n### 3. Uzun Mesafeli Kontrol\nGörünmez optik kablolar aracılığıyla uzun mesafeli ve düşük gecikmeli kontrol sinyali iletimi elde edin ve İHA'ların çalışma doğruluğunu ve tepki hızını artırın.\n\n### 4. Görev Ekipmanları Bağlantısı\nVerimli veri iletimini sağlamak için drone tarafından taşınan kamera, radar vb. görev ekipmanlarını bağlayın.\n\n![Görünmez Fiber Kamera Bağlantısı](img/invisible-fiber-camera-connection.jpg)\n*Görünmez fiber optik kablo ile kamera ve sensör bağlantıları*\n\n## Teknik Avantajlar\n\n### Bant Genişliği\nGörünmez fiber optik kablolar, geleneksel kablosuz sistemlere kıyasla çok daha yüksek bant genişliği sunar. Bu özellik, 4K ve 8K video akışları, yüksek çözünürlüklü görüntüleme ve büyük veri dosyalarının aktarımı için idealdir.\n\n### Gecikme Süresi\nFiber optik kablolar, elektriksel kablolara kıyasla çok daha düşük gecikme süresi sağlar. Bu, gerçek zamanlı kontrol ve müdahale operasyonlarında kritik öneme sahiptir.\n\n### Güvenlik\nFiziksel kablo üzerinden yapılan veri aktarımı, dış müdahalelere karşı çok daha güvenlidir. Bu özellik, askeri ve güvenlik uygulamalarında vazgeçilmezdir.\n\n![Görünmez Fiber Drone Bileşenleri](img/invisible-fiber-drone-components.jpg)\n*Görünmez fiber optik kablo ile drone bileşenleri entegrasyonu*\n\n## Kullanım Alanları\n\n### Askeri Uygulamalar\nGörünmez fiber optik kablolar, askeri İHA'larda güvenli iletişim, gerçek zamanlı istihbarat toplama ve hedef tespiti gibi kritik operasyonlarda kullanılır.\n\n![Görünmez Fiber Askeri Kullanım](img/invisible-fiber-military-use.jpg)\n*Askeri İHA'larda görünmez fiber optik kablo uygulamaları*\n\n### Endüstriyel Uygulamalar\nBüyük endüstriyel tesislerde, altyapı denetimi, güvenlik gözetimi ve acil müdahale operasyonlarında görünmez fiber optik kablolar kullanılır.\n\n![Görünmez Fiber Endüstriyel Uygulama](img/invisible-fiber-industrial-application.jpg)\n*Endüstriyel İHA'larda görünmez fiber optik kablo kullanımı*\n\n### Araştırma ve Geliştirme\nBilimsel araştırmalar, çevre izleme ve veri toplama operasyonlarında görünmez fiber optik kablolar tercih edilir.\n\n## Gelecek Perspektifi\n\nGörünmez fiber optik kablo teknolojisi, İHA endüstrisinde hızla gelişmekte olan bir alandır. Gelecekte:\n\n- Daha da hafif ve esnek malzemeler\n- Gelişmiş şeffaflık teknolojileri\n- Daha yüksek bant genişliği kapasiteleri\n- Otomatik kablo yönetim sistemleri\n\nbeklenmektedir.\n\n## Sonuç\n\nİHA için görünmez fiber optik kablo, modern drone teknolojisinin en önemli gelişmelerinden biridir. Görsel gizlilik, yüksek performans ve güvenilirlik özellikleri ile askeri, endüstriyel ve ticari uygulamalarda vazgeçilmez bir teknoloji haline gelmiştir.\n\n**Hangzhou Softel Optik A.Ş., Ltd.** gibi profesyonel üreticiler, bu alanda sürekli AR-GE çalışmaları yürüterek teknolojinin gelişimine katkı sağlamaktadır.\n\n## Kaynaklar\n\n- [Softel FTTH - İHA İçin Görünmez Fiber Optik Kablo](https://tr.softelftth.com/news/what-is-invisible-fiber-optic-cable-for-uav-84373639.html)\n- Hangzhou Softel Optik A.Ş., Ltd. - Teknik Dokümantasyon\n- Fiber Optik Kablo Teknolojileri\n- İHA İletişim Sistemleri\n\n---\n\n*Bu rehber, İHA için görünmez fiber optik kablo teknolojisinin temel özelliklerini, uygulamalarını ve gelecekteki potansiyelini kapsamlı bir şekilde ele almaktadır.*",
      "tags": [
        "görünmez-fiber-optik",
        "iha",
        "drone",
        "fiber-optik",
        "kablo",
        "teknoloji",
        "iletişim",
        "türkçe",
        "rehber"
      ],
      "createdAt": "2025-01-08T00:00:00.000Z",
      "updatedAt": "2025-01-08T00:00:00.000Z",
      "images": [
        {
          "url": "img/invisible-optical-cable.jpg",
          "alt": "Görünmez Fiber Optik Kablo",
          "caption": "İHA için görünmez fiber optik kablo - Şeffaf ve hafif tasarım"
        },
        {
          "url": "img/factory-transparent-fiber-optic-cable.jpg",
          "alt": "Fabrika Şeffaf Fiber Optik Kablo",
          "caption": "Fabrika üretimi şeffaf fiber optik kablo - Özel malzeme ve tasarım"
        },
        {
          "url": "img/invisible-fiber-drone-application.jpg",
          "alt": "İHA Görünmez Fiber Uygulaması",
          "caption": "İHA'da görünmez fiber optik kablo uygulaması - Esnek ve dayanıklı tasarım"
        },
        {
          "url": "img/invisible-fiber-data-transmission.jpg",
          "alt": "Görünmez Fiber Veri Aktarımı",
          "caption": "Görünmez fiber optik kablo ile yüksek hızlı veri aktarımı"
        },
        {
          "url": "img/invisible-fiber-camera-connection.jpg",
          "alt": "Görünmez Fiber Kamera Bağlantısı",
          "caption": "Görünmez fiber optik kablo ile kamera ve sensör bağlantıları"
        },
        {
          "url": "img/invisible-fiber-drone-components.jpg",
          "alt": "Görünmez Fiber Drone Bileşenleri",
          "caption": "Görünmez fiber optik kablo ile drone bileşenleri entegrasyonu"
        },
        {
          "url": "img/invisible-fiber-military-use.jpg",
          "alt": "Görünmez Fiber Askeri Kullanım",
          "caption": "Askeri İHA'larda görünmez fiber optik kablo uygulamaları"
        },
        {
          "url": "img/invisible-fiber-industrial-application.jpg",
          "alt": "Görünmez Fiber Endüstriyel Uygulama",
          "caption": "Endüstriyel İHA'larda görünmez fiber optik kablo kullanımı"
        }
      ],
      "author": "FEZA Drone Sözlüğü",
      "source": "https://tr.softelftth.com/news/what-is-invisible-fiber-optic-cable-for-uav-84373639.html",
      "wordCount": 2500,
      "readingTime": "12 dakika",
      "difficulty": "Orta",
      "relatedArticles": [
        "fiber-optik-drone-teknolojisi",
        "iha-iletişim-sistemleri",
        "drone-güvenlik-teknolojileri"
      ]
    }
  ]
}